msiAlign/__init__.py
msiAlign/__main__.py
msiAlign/downcore_profile.py
msiAlign/func.py
msiAlign/menubar.py
msiAlign/metadata_crawler.py
msiAlign/objects.py
msiAlign/parser.py
msiAlign/rclick.py
msiAlign/shinyApp.py
msiAlign/to1d.py
msialign-1.1.1.dist-info/licenses/LICENSE
msialign-1.1.1.dist-info/METADATA
msialign-1.1.1.dist-info/WHEEL
msialign-1.1.1.dist-info/entry_points.txt
msialign-1.1.1.dist-info/top_level.txt
msialign-1.1.1.dist-info/RECORD
