Metadata-Version: 2.4
Name: msiAlign
Version: 1.1.1
Summary: A simple tool to manually register multiple MSI-related images
Author-email: Weimin Liu <wliu@marum.de>
License: MIT License
License-File: LICENSE
Requires-Dist: numpy
Requires-Dist: pillow
Requires-Dist: pandas
Requires-Dist: matplotlib
Requires-Dist: shiny
Dynamic: license-file
